dspip/__init__.py
dspip/crypto.py
dspip/delivery.py
dspip/directory.py
dspip/dns.py
dspip/dnssec.py
dspip/payload.py
dspip/qr.py
dspip/revocation.py
dspip/types.py
dspip/verify.py
dspip-1.0.1.dist-info/METADATA
dspip-1.0.1.dist-info/WHEEL
dspip-1.0.1.dist-info/top_level.txt
dspip-1.0.1.dist-info/RECORD
