Metadata-Version: 2.4
Name: dspip
Version: 1.0.1
Summary: Digital Signing of Physical Items Protocol SDK - Official Python implementation
Home-page: https://github.com/midwestcyber/dspip-python
Author: Andy Boell
Author-email: "Midwest Cyber, LLC" <contact@dspip.io>
License-Expression: MIT
Project-URL: Homepage, https://dspip.dev
Project-URL: Documentation, https://dspip.dev/docs
Project-URL: Repository, https://github.com/MidwestCyberLLC/dspip.dev
Project-URL: Issues, https://github.com/MidwestCyberLLC/dspip.dev/issues
Keywords: dspip,digital-signature,shipping,qr-code,cryptography,secp256k1,ed25519,ecies,dns,pki
Classifier: Development Status :: 4 - Beta
Classifier: Intended Audience :: Developers
Classifier: Operating System :: OS Independent
Classifier: Programming Language :: Python :: 3
Classifier: Programming Language :: Python :: 3.9
Classifier: Programming Language :: Python :: 3.10
Classifier: Programming Language :: Python :: 3.11
Classifier: Programming Language :: Python :: 3.12
Classifier: Topic :: Security :: Cryptography
Classifier: Topic :: Software Development :: Libraries :: Python Modules
Requires-Python: >=3.8
Requires-Dist: coincurve>=19.0.0
Requires-Dist: pynacl>=1.5.0
Requires-Dist: cryptography>=41.0.0
Requires-Dist: qrcode[pil]>=7.4.0
Requires-Dist: httpx>=0.25.0
Provides-Extra: dev
Requires-Dist: pytest>=7.0.0; extra == "dev"
Requires-Dist: pytest-asyncio>=0.21.0; extra == "dev"
Requires-Dist: mypy>=1.0.0; extra == "dev"
Requires-Dist: ruff>=0.1.0; extra == "dev"
Dynamic: author
Dynamic: home-page
Dynamic: requires-python
